alicefluentcheck/AliceAnswer.py
alicefluentcheck/AliceEntity.py
alicefluentcheck/AliceIntents.py
alicefluentcheck/AliceRequest.py
alicefluentcheck/__init__.py
alicefluentcheck/chain.py
alicefluentcheck/constants.py
alicefluentcheck-2.1.1.dist-info/LICENSE
alicefluentcheck-2.1.1.dist-info/METADATA
alicefluentcheck-2.1.1.dist-info/WHEEL
alicefluentcheck-2.1.1.dist-info/top_level.txt
alicefluentcheck-2.1.1.dist-info/RECORD
