Metadata-Version: 2.1
Name: alicefluentcheck
Version: 2.1.1
Summary: Подготовка запросов для тестирования навыков Яндекс.Алисы
Home-page: https://github.com/KrapivinAndrey/YaAlice_FluentTesting
Author: a.krapivin
Author-email: krapivin_andrey@mail.ru
Maintainer: a.krapivin
Maintainer-email: krapivin_andrey@mail.ru
License: UNKNOWN
Platform: UNKNOWN
Classifier: Programming Language :: Python :: 3.7
Classifier: Programming Language :: Python :: 3.8
Classifier: Programming Language :: Python :: 3.9
Classifier: Programming Language :: Python :: 3.10
Classifier: Operating System :: OS Independent
Requires-Python: >=3.7
License-File: LICENSE
Requires-Dist: fluentcheck
